fta/__init__.py
fta/main.py
fta/pantulipy.py
fta-0.0.16.dist-info/METADATA
fta-0.0.16.dist-info/WHEEL
fta-0.0.16.dist-info/top_level.txt
fta-0.0.16.dist-info/RECORD
