Metadata-Version: 2.4
Name: fta
Version: 0.0.16
Home-page: https://github.com/voidful/FTA
Author: Voidful
Author-email: voidful.stack@gmail.com
Keywords: finance
Classifier: Development Status :: 4 - Beta
Classifier: License :: OSI Approved :: Apache Software License
Classifier: Programming Language :: Python
Requires-Dist: numpy==1.23.5; python_version < "3.12"
Requires-Dist: numba==0.56.4; python_version < "3.12"
Requires-Dist: llvmlite==0.39.1; python_version < "3.12"
Requires-Dist: pandas==1.5.3; python_version < "3.12"
Requires-Dist: scipy==1.10.1; python_version < "3.12"
Requires-Dist: scikit-learn==1.3.2; python_version < "3.12"
Requires-Dist: matplotlib==3.7.5; python_version < "3.12"
Requires-Dist: numpy>=2.1; python_version >= "3.12"
Requires-Dist: numba<0.62,>=0.61; python_version >= "3.12"
Requires-Dist: llvmlite<0.45,>=0.44; python_version >= "3.12"
Requires-Dist: pandas>=2.2.3; python_version >= "3.12"
Requires-Dist: scipy>=1.14.1; python_version >= "3.12"
Requires-Dist: scikit-learn>=1.6; python_version >= "3.12"
Requires-Dist: matplotlib>=3.10; python_version >= "3.12"
Requires-Dist: imageio==2.37.0
Requires-Dist: requests==2.32.5
Requires-Dist: jinja2==3.1.6
Requires-Dist: nlp2==1.9.4
Requires-Dist: twstock==1.4.0
Requires-Dist: yfinance==0.2.66
Requires-Dist: vectorbt
Requires-Dist: lxml==4.9.4; python_version < "3.12"
Requires-Dist: lxml>=5.3; python_version >= "3.12"
Requires-Dist: pandas_ta==0.3.14b0; python_version < "3.12"
Requires-Dist: pandas-ta-openbb>=0.4.22; python_version >= "3.12"
Dynamic: author
Dynamic: author-email
Dynamic: classifier
Dynamic: description
Dynamic: description-content-type
Dynamic: home-page
Dynamic: keywords
Dynamic: requires-dist
